capedu/__init__.py
capedu/cap.py
capedu-0.2.dist-info/METADATA
capedu-0.2.dist-info/WHEEL
capedu-0.2.dist-info/top_level.txt
capedu-0.2.dist-info/RECORD
