Metadata-Version: 2.1
Name: capedu
Version: 0.2
Summary: Una biblioteca para calcular el Coeficiente de Adecuación Patrimonial en Bolivia
Home-page: https://github.com/msalaztor
Author: Mario Rene Salazar Torres
Author-email: mrsalazar@outlook.com
License: UNKNOWN
Platform: UNKNOWN
Classifier: License :: OSI Approved :: MIT License
Classifier: Programming Language :: Python :: 3
Classifier: Programming Language :: Python :: 3.7
Classifier: Programming Language :: Python :: 3.8
Classifier: Programming Language :: Python :: 3.9
